dynamodb_counter/__init__.py
dynamodb_counter/counter.py
dynamodb_counter/reserved.py
dynamodb_counter/serializers.py
dynamodb_counter-0.1.2.dist-info/LICENSE
dynamodb_counter-0.1.2.dist-info/WHEEL
dynamodb_counter-0.1.2.dist-info/METADATA
dynamodb_counter-0.1.2.dist-info/RECORD
